{
  "gitSyncId": "669e6cd6ae21844540eb5cde_f0e0a873-6f1d-4fa4-9547-639e2f960538",
  "id": "Page1__$p31$_p3.myFun2",
  "isPublic": true,
  "moduleInstanceId": "Page1_p31",
  "pluginId": "js-plugin",
  "pluginType": "JS",
  "rootModuleInstanceId": "Page1_p31",
  "unpublishedAction": {
    "clientSideExecution": true,
    "collectionId": "Page1__$p31$_p3",
    "confirmBeforeExecute": false,
    "contextType": "PAGE",
    "datasource": {
      "isAutoGenerated": false,
      "name": "UNUSED_DATASOURCE",
      "pluginId": "js-plugin"
    },
    "executeOnLoad": false,
    "fullyQualifiedName": "_$p31$_p3.myFun2",
    "name": "myFun2",
    "pageId": "Page1",
    "userSetOnLoad": false
  }
}